androidemulator/__init__.py
androidemulator/adb.py
androidemulator/android_tests.py
androidemulator/avdmanager.py
androidemulator/cli.py
androidemulator/common.py
androidemulator/emulator.py
androidemulator/execute.py
androidemulator/sdkmanager.py
androidemulator/uninstallapp.py
androidemulator/assets/example.txt
androidemulator/testing/__init__.py
androidemulator/testing/watchdog.py
androidemulator-1.0.0.dist-info/LICENSE
androidemulator-1.0.0.dist-info/METADATA
androidemulator-1.0.0.dist-info/WHEEL
androidemulator-1.0.0.dist-info/entry_points.txt
androidemulator-1.0.0.dist-info/top_level.txt
androidemulator-1.0.0.dist-info/RECORD
