Metadata-Version: 2.1
Name: androidemulator
Version: 1.0.0
Summary: Controls the Android Emulator from python API bindings
Home-page: https://github.com/zackees/androidemulator
Maintainer: Zachary Vorhies
License: BSD 3-Clause License
Keywords: template-python-cmd
Classifier: Programming Language :: Python :: 3
Requires-Python: >=3.7
License-File: LICENSE
Requires-Dist: zcmds (>=1.4.2)
